{
  "id": "f0cf7de2-682f-4f75-8b50-0e69016bb316",
  "prevId": "00000000-0000-0000-0000-000000000000",
  "version": "5",
  "dialect": "pg",
  "tables": {
    "banners": {
      "name": "banners",
      "schema": "",
      "columns": {
        "id": {
          "name": "id",
          "type": "varchar(128)",
          "primaryKey": true,
          "notNull": true
        },
        "title": {
          "name": "title",
          "type": "text",
          "primaryKey": false,
          "notNull": true
        },
        "description": {
          "name": "description",
          "type": "text",
          "primaryKey": false,
          "notNull": false
        },
        "image_uri": {
          "name": "image_uri",
          "type": "text",
          "primaryKey": false,
          "notNull": false
        },
        "link": {
          "name": "link",
          "type": "text",
          "primaryKey": false,
          "notNull": false
        },
        "is_active": {
          "name": "is_active",
          "type": "boolean",
          "primaryKey": false,
          "notNull": false,
          "default": true
        },
        "created_at": {
          "name": "created_at",
          "type": "timestamp",
          "primaryKey": false,
          "notNull": false,
          "default": "now()"
        }
      },
      "indexes": {},
      "foreignKeys": {},
      "compositePrimaryKeys": {},
      "uniqueConstraints": {}
    },
    "categories": {
      "name": "categories",
      "schema": "",
      "columns": {
        "id": {
          "name": "id",
          "type": "varchar(128)",
          "primaryKey": true,
          "notNull": true
        },
        "name": {
          "name": "name",
          "type": "text",
          "primaryKey": false,
          "notNull": true
        },
        "icon_name": {
          "name": "icon_name",
          "type": "text",
          "primaryKey": false,
          "notNull": false
        },
        "created_at": {
          "name": "created_at",
          "type": "timestamp",
          "primaryKey": false,
          "notNull": false,
          "default": "now()"
        }
      },
      "indexes": {},
      "foreignKeys": {},
      "compositePrimaryKeys": {},
      "uniqueConstraints": {}
    },
    "cities": {
      "name": "cities",
      "schema": "",
      "columns": {
        "id": {
          "name": "id",
          "type": "varchar(128)",
          "primaryKey": true,
          "notNull": true
        },
        "name": {
          "name": "name",
          "type": "text",
          "primaryKey": false,
          "notNull": true
        },
        "state": {
          "name": "state",
          "type": "text",
          "primaryKey": false,
          "notNull": false
        },
        "zip_code": {
          "name": "zip_code",
          "type": "text",
          "primaryKey": false,
          "notNull": false
        },
        "created_at": {
          "name": "created_at",
          "type": "timestamp",
          "primaryKey": false,
          "notNull": false,
          "default": "now()"
        }
      },
      "indexes": {},
      "foreignKeys": {},
      "compositePrimaryKeys": {},
      "uniqueConstraints": {}
    },
    "companies": {
      "name": "companies",
      "schema": "",
      "columns": {
        "id": {
          "name": "id",
          "type": "varchar(128)",
          "primaryKey": true,
          "notNull": true
        },
        "name": {
          "name": "name",
          "type": "text",
          "primaryKey": false,
          "notNull": true
        },
        "slogan": {
          "name": "slogan",
          "type": "text",
          "primaryKey": false,
          "notNull": false
        },
        "description": {
          "name": "description",
          "type": "text",
          "primaryKey": false,
          "notNull": false
        },
        "address": {
          "name": "address",
          "type": "text",
          "primaryKey": false,
          "notNull": false
        },
        "email": {
          "name": "email",
          "type": "text",
          "primaryKey": false,
          "notNull": false
        },
        "phone": {
          "name": "phone",
          "type": "text",
          "primaryKey": false,
          "notNull": false
        },
        "whatsapp": {
          "name": "whatsapp",
          "type": "text",
          "primaryKey": false,
          "notNull": false
        },
        "instagram": {
          "name": "instagram",
          "type": "text",
          "primaryKey": false,
          "notNull": false
        },
        "website": {
          "name": "website",
          "type": "text",
          "primaryKey": false,
          "notNull": false
        },
        "banner_hex": {
          "name": "banner_hex",
          "type": "text",
          "primaryKey": false,
          "notNull": false
        },
        "banner_uri": {
          "name": "banner_uri",
          "type": "text",
          "primaryKey": false,
          "notNull": false
        },
        "logo_uri": {
          "name": "logo_uri",
          "type": "text",
          "primaryKey": false,
          "notNull": false
        },
        "is_active": {
          "name": "is_active",
          "type": "boolean",
          "primaryKey": false,
          "notNull": false,
          "default": true
        },
        "city_id": {
          "name": "city_id",
          "type": "varchar(128)",
          "primaryKey": false,
          "notNull": false
        },
        "created_at": {
          "name": "created_at",
          "type": "timestamp",
          "primaryKey": false,
          "notNull": false,
          "default": "now()"
        }
      },
      "indexes": {},
      "foreignKeys": {
        "companies_city_id_cities_id_fk": {
          "name": "companies_city_id_cities_id_fk",
          "tableFrom": "companies",
          "tableTo": "cities",
          "columnsFrom": [
            "city_id"
          ],
          "columnsTo": [
            "id"
          ],
          "onDelete": "no action",
          "onUpdate": "no action"
        }
      },
      "compositePrimaryKeys": {},
      "uniqueConstraints": {}
    },
    "companies_to_categories": {
      "name": "companies_to_categories",
      "schema": "",
      "columns": {
        "id": {
          "name": "id",
          "type": "varchar(128)",
          "primaryKey": true,
          "notNull": true
        },
        "company_id": {
          "name": "company_id",
          "type": "varchar(128)",
          "primaryKey": false,
          "notNull": false
        },
        "category_id": {
          "name": "category_id",
          "type": "varchar(128)",
          "primaryKey": false,
          "notNull": false
        }
      },
      "indexes": {},
      "foreignKeys": {
        "companies_to_categories_company_id_companies_id_fk": {
          "name": "companies_to_categories_company_id_companies_id_fk",
          "tableFrom": "companies_to_categories",
          "tableTo": "companies",
          "columnsFrom": [
            "company_id"
          ],
          "columnsTo": [
            "id"
          ],
          "onDelete": "no action",
          "onUpdate": "no action"
        },
        "companies_to_categories_category_id_categories_id_fk": {
          "name": "companies_to_categories_category_id_categories_id_fk",
          "tableFrom": "companies_to_categories",
          "tableTo": "categories",
          "columnsFrom": [
            "category_id"
          ],
          "columnsTo": [
            "id"
          ],
          "onDelete": "no action",
          "onUpdate": "no action"
        }
      },
      "compositePrimaryKeys": {},
      "uniqueConstraints": {}
    },
    "offers": {
      "name": "offers",
      "schema": "",
      "columns": {
        "id": {
          "name": "id",
          "type": "varchar(128)",
          "primaryKey": true,
          "notNull": true
        },
        "title": {
          "name": "title",
          "type": "text",
          "primaryKey": false,
          "notNull": true
        },
        "description": {
          "name": "description",
          "type": "text",
          "primaryKey": false,
          "notNull": false
        },
        "image_uri": {
          "name": "image_uri",
          "type": "text",
          "primaryKey": false,
          "notNull": false
        },
        "link": {
          "name": "link",
          "type": "text",
          "primaryKey": false,
          "notNull": false
        },
        "is_active": {
          "name": "is_active",
          "type": "boolean",
          "primaryKey": false,
          "notNull": false,
          "default": true
        },
        "company_id": {
          "name": "company_id",
          "type": "varchar(128)",
          "primaryKey": false,
          "notNull": false
        },
        "created_at": {
          "name": "created_at",
          "type": "timestamp",
          "primaryKey": false,
          "notNull": false,
          "default": "now()"
        }
      },
      "indexes": {},
      "foreignKeys": {
        "offers_company_id_companies_id_fk": {
          "name": "offers_company_id_companies_id_fk",
          "tableFrom": "offers",
          "tableTo": "companies",
          "columnsFrom": [
            "company_id"
          ],
          "columnsTo": [
            "id"
          ],
          "onDelete": "no action",
          "onUpdate": "no action"
        }
      },
      "compositePrimaryKeys": {},
      "uniqueConstraints": {}
    },
    "root_users": {
      "name": "root_users",
      "schema": "",
      "columns": {
        "id": {
          "name": "id",
          "type": "varchar(128)",
          "primaryKey": true,
          "notNull": true
        },
        "name": {
          "name": "name",
          "type": "text",
          "primaryKey": false,
          "notNull": true
        },
        "email": {
          "name": "email",
          "type": "text",
          "primaryKey": false,
          "notNull": false
        },
        "password": {
          "name": "password",
          "type": "text",
          "primaryKey": false,
          "notNull": false
        },
        "is_active": {
          "name": "is_active",
          "type": "boolean",
          "primaryKey": false,
          "notNull": false,
          "default": true
        },
        "created_at": {
          "name": "created_at",
          "type": "timestamp",
          "primaryKey": false,
          "notNull": false,
          "default": "now()"
        }
      },
      "indexes": {},
      "foreignKeys": {},
      "compositePrimaryKeys": {},
      "uniqueConstraints": {}
    },
    "users": {
      "name": "users",
      "schema": "",
      "columns": {
        "id": {
          "name": "id",
          "type": "varchar(128)",
          "primaryKey": true,
          "notNull": true
        },
        "name": {
          "name": "name",
          "type": "text",
          "primaryKey": false,
          "notNull": true
        },
        "email": {
          "name": "email",
          "type": "text",
          "primaryKey": false,
          "notNull": false
        },
        "password": {
          "name": "password",
          "type": "text",
          "primaryKey": false,
          "notNull": false
        },
        "is_active": {
          "name": "is_active",
          "type": "boolean",
          "primaryKey": false,
          "notNull": false,
          "default": true
        },
        "city_id": {
          "name": "city_id",
          "type": "varchar(128)",
          "primaryKey": false,
          "notNull": false
        },
        "created_at": {
          "name": "created_at",
          "type": "timestamp",
          "primaryKey": false,
          "notNull": false,
          "default": "now()"
        }
      },
      "indexes": {},
      "foreignKeys": {
        "users_city_id_cities_id_fk": {
          "name": "users_city_id_cities_id_fk",
          "tableFrom": "users",
          "tableTo": "cities",
          "columnsFrom": [
            "city_id"
          ],
          "columnsTo": [
            "id"
          ],
          "onDelete": "no action",
          "onUpdate": "no action"
        }
      },
      "compositePrimaryKeys": {},
      "uniqueConstraints": {}
    }
  },
  "enums": {},
  "schemas": {},
  "_meta": {
    "columns": {},
    "schemas": {},
    "tables": {}
  }
}